mrfdictionary/__init__.py
mrfdictionary/dictionary.py
mrfdictionary/sequence.py
mrfdictionary/simulation.py
mrfdictionary-0.0.2.dist-info/LICENSE
mrfdictionary-0.0.2.dist-info/METADATA
mrfdictionary-0.0.2.dist-info/WHEEL
mrfdictionary-0.0.2.dist-info/top_level.txt
mrfdictionary-0.0.2.dist-info/RECORD
